bead_it/__init__.py
bead_it/count.py
bead_it-0.1.dist-info/METADATA
bead_it-0.1.dist-info/WHEEL
bead_it-0.1.dist-info/entry_points.txt
bead_it-0.1.dist-info/top_level.txt
bead_it-0.1.dist-info/RECORD
