Metadata-Version: 2.1
Name: bead-it
Version: 0.1
Summary: A simple code to count number of pixels in an image
Home-page: https://github.com/DevinHA/bead_it.git
Author: huangzijing
Author-email: 529086967@qq.com
License: UNKNOWN
Platform: UNKNOWN
Requires-Dist: webcolors
Requires-Dist: Pillow (>=5.3.0)
